tutorial-2/src/alu.v
module alu (
    input  wire [2:0] op,
    input  wire [7:0] A,
    input  wire [7:0] B,
    output reg  [7:0] Y,
    output wire       zero,
    output wire       negative,
    output wire       overflow,
    output wire       carry
);
    reg [8:0] sum_ext;

    assign zero     = (Y == 8'h00);
    assign negative = Y[7];
    assign carry    = (op == 3'b000 || op == 3'b001) ? sum_ext[8] : 1'b0;
    
    // Signed overflow for ADD and SUB
    assign overflow = (op == 3'b000) ? (~(A[7] ^ B[7]) & (A[7] ^ Y[7])) :
                      (op == 3'b001) ? ((A[7] ^ B[7])  & (A[7] ^ Y[7])) : 1'b0;

    always @(*) begin
        sum_ext = 9'b0;
        case (op)
            3'b000: begin
                sum_ext = A + B;
                Y       = sum_ext[7:0];
            end
            3'b001: begin
                sum_ext = A - B;
                Y       = sum_ext[7:0];
            end
            3'b010: begin 
                Y       = A & B;
            end
            3'b011: begin 
                Y       = A | B;
            end
            3'b100: begin 
                Y       = A ^ B;
            end
            3'b101: begin 
                Y       = ($signed(A) < $signed(B)) ? 8'h01 : 8'h00;
            end
            default: begin
                Y       = 8'h00;
            end
        endcase
    end
endmodule

tutorial-2/test/tb/tb_alu.v
`timescale 1ns/1ps

module tb_alu;
    reg  [2:0] op;
    reg  [7:0] A, B;
    wire [7:0] Y;
    wire       zero, negative, overflow, carry;

    alu uut (
        .op(op), .A(A), .B(B), .Y(Y),
        .zero(zero), .negative(negative), .overflow(overflow), .carry(carry)
    );

    integer i;

    initial begin
        $dumpfile("wave_alu.vcd");
        $dumpvars(0, tb_alu);

        // 1. ADD Test with Carry and Overflow
        op = 3'b000; A = 8'd200; B = 8'd100; #10; 
        op = 3'b000; A = 8'd120; B = 8'd10;  #10; 

        // 2. SUB Test with Zero and Negative flags
        op = 3'b001; A = 8'd50;  B = 8'd50;  #10; 
        op = 3'b001; A = 8'd10;  B = 8'd20;  #10; 

        // 3. Bitwise Logic
        op = 3'b010; A = 8'hFF; B = 8'h0F; #10; 
        op = 3'b011; A = 8'hF0; B = 8'h0F; #10; 
        op = 3'b100; A = 8'hAA; B = 8'hAA; #10;

        // 4. SLT Test
        op = 3'b101; A = 8'hFE; B = 8'h05; #10; 

        // 5. Randomized Testing (100+ Iterations)
        for (i = 0; i < 100; i = i + 1) begin
            op = $urandom_range(0, 5);
            A  = $urandom;
            B  = $urandom;
            #10;
        end

        $finish;
    end
endmodule

tutorial-2/test/wave/wave_alu.vcd
$date
	Sun Sep 27 21:58:03 2026
$end
$version
	Icarus Verilog
$end
$timescale
	1ps
$end
$scope module tb_alu $end
$var wire 1 ! zero $end
$var wire 1 " overflow $end
$var wire 1 # negative $end
$var wire 1 $ carry $end
$var wire 8 % Y [7:0] $end
$var reg 8 & A [7:0] $end
$var reg 8 ' B [7:0] $end
$var reg 3 ( op [2:0] $end
$var integer 32 ) i [31:0] $end
$scope module uut $end
$var wire 8 * A [7:0] $end
$var wire 8 + B [7:0] $end
$var wire 3 , op [2:0] $end
$var wire 1 ! zero $end
$var wire 1 " overflow $end
$var wire 1 # negative $end
$var wire 1 $ carry $end
$var reg 8 - Y [7:0] $end
$var reg 9 . sum_ext [8:0] $end
$upscope $end
$upscope $end
$enddefinitions $end
#0
$dumpvars
b100101100 .
b101100 -
b0 ,
b1100100 +
b11001000 *
bx )
b0 (
b1100100 '
b11001000 &
b101100 %
1$
0#
0"
0!
$end
#10000
1"
0$
1#
b10000010 %
b10000010 -
b10000010 .
b1010 '
b1010 +
b1111000 &
b1111000 *
#20000
0#
1!
b0 %
b0 -
b0 .
0"
b110010 '
b110010 +
b110010 &
b110010 *
b1 (
b1 ,
#30000
1$
1#
0!
b11110110 %
b11110110 -
b111110110 .
b10100 '
b10100 +
b1010 &
b1010 *
#40000
0#
0$
b1111 %
b1111 -
b0 .
b1111 '
b1111 +
b11111111 &
b11111111 *
b10 (
b10 ,
#50000
1#
b11111111 %
b11111111 -
b11110000 &
b11110000 *
b11 (
b11 ,
#60000
0#
1!
b0 %
b0 -
b10101010 '
b10101010 +
b10101010 &
b10101010 *
b100 (
b100 ,
#70000
0!
b1 %
b1 -
b101 '
b101 +
b11111110 &
b11111110 *
b101 (
b101 ,
#80000
1#
b10001001 %
b10001001 -
b1001 '
b1001 +
b10000001 &
b10000001 *
b11 (
b11 ,
b0 )
#90000
1"
1$
b10000000 %
b10000000 -
b110000000 .
b10001101 '
b10001101 +
b1101 &
b1101 *
b1 (
b1 ,
b1 )
#100000
0"
0$
0#
b10001 %
b10001 -
b10001 .
b1 '
b1 +
b10010 &
b10010 *
b10 )
#110000
b1111111 %
b1111111 -
b0 .
b111101 '
b111101 +
b1110110 &
b1110110 *
b11 (
b11 ,
b11 )
#120000
b1 %
b1 -
b11111001 '
b11111001 +
b10001100 &
b10001100 *
b101 (
b101 ,
b100 )
#130000
1#
b10000000 %
b10000000 -
b10101010 '
b10101010 +
b11000101 &
b11000101 *
b10 (
b10 ,
b101 )
#140000
0#
1!
b0 %
b0 -
b10010 '
b10010 +
b1110111 &
b1110111 *
b101 (
b101 ,
b110 )
#150000
0!
b111100 %
b111100 -
b11001110 '
b11001110 +
b11110010 &
b11110010 *
b100 (
b100 ,
b111 )
#160000
b1000100 %
b1000100 -
b1011100 '
b1011100 +
b11000101 &
b11000101 *
b10 (
b10 ,
b1000 )
#170000
b100101 %
b100101 -
b1100101 '
b1100101 +
b101101 &
b101101 *
b1001 )
#180000
1"
1$
1#
b10001010 %
b10001010 -
b110001010 .
b10000000 '
b10000000 +
b1010 &
b1010 *
b1 (
b1 ,
b1010 )
#190000
0$
0"
b10111111 %
b10111111 -
b0 .
b10011101 '
b10011101 +
b10101010 &
b10101010 *
b11 (
b11 ,
b1011 )
#200000
0#
b110 %
b110 -
b110 .
b1101 '
b1101 +
b10011 &
b10011 *
b1 (
b1 ,
b1100 )
#210000
1$
b1000000 %
b1000000 -
b101000000 .
b11010101 '
b11010101 +
b1101011 &
b1101011 *
b0 (
b0 ,
b1101 )
#220000
0$
1#
b11001011 %
b11001011 -
b11001011 .
b11101 '
b11101 +
b10101110 &
b10101110 *
b1110 )
#230000
0#
b10 %
b10 -
b0 .
b1010 '
b1010 +
b100011 &
b100011 *
b10 (
b10 ,
b1111 )
#240000
b110000 %
b110000 -
b11110010 '
b11110010 +
b111100 &
b111100 *
b10000 )
#250000
1#
b10011001 %
b10011001 -
b11011000 '
b11011000 +
b1000001 &
b1000001 *
b100 (
b100 ,
b10001 )
#260000
0#
b1100010 %
b1100010 -
b11101011 '
b11101011 +
b10001001 &
b10001001 *
b10010 )
#270000
1!
b0 %
b0 -
b10101110 '
b10101110 +
b11000110 &
b11000110 *
b101 (
b101 ,
b10011 )
#280000
0!
b1010 %
b1010 -
b1011 '
b1011 +
b101010 &
b101010 *
b10 (
b10 ,
b10100 )
#290000
1"
b110110 %
b110110 -
b110110 .
b1001111 '
b1001111 +
b10000101 &
b10000101 *
b1 (
b1 ,
b10101 )
#300000
1#
b10111000 %
b10111000 -
b10111000 .
1"
b1111110 '
b1111110 +
b111010 &
b111010 *
b0 (
b0 ,
b10110 )
#310000
b11111001 %
b11111001 -
b0 .
0"
b11011001 '
b11011001 +
b11110001 &
b11110001 *
b11 (
b11 ,
b10111 )
#320000
b11010011 %
b11010011 -
b10011111 '
b10011111 +
b1001100 &
b1001100 *
b100 (
b100 ,
b11000 )
#330000
0#
b1001111 %
b1001111 -
b10110111 '
b10110111 +
b11111000 &
b11111000 *
b11001 )
#340000
b1 %
b1 -
b1 .
b1011011 '
b1011011 +
b1011100 &
b1011100 *
b1 (
b1 ,
b11010 )
#350000
1#
b10011001 %
b10011001 -
b0 .
b11010000 '
b11010000 +
b1001001 &
b1001001 *
b100 (
b100 ,
b11011 )
#360000
0#
b10000 %
b10000 -
b10010110 '
b10010110 +
b1010001 &
b1010001 *
b10 (
b10 ,
b11100 )
#370000
1#
b11001010 %
b11001010 -
b11001000 '
b11001000 +
b11000010 &
b11000010 *
b11 (
b11 ,
b11101 )
#380000
0#
b101011 %
b101011 -
b101011 .
b10010 '
b10010 +
b111101 &
b111101 *
b1 (
b1 ,
b11110 )
#390000
b110100 %
b110100 -
b110100 .
b111001 '
b111001 +
b1101101 &
b1101101 *
b11111 )
#400000
1#
b11010111 %
b11010111 -
b0 .
b10000101 '
b10000101 +
b11010011 &
b11010011 *
b11 (
b11 ,
b100000 )
#410000
0#
b10010 %
b10010 -
b10010 .
b1001001 '
b1001001 +
b1011011 &
b1011011 *
b1 (
b1 ,
b100001 )
#420000
1"
1#
b10000010 %
b10000010 -
b10000010 .
b1011000 '
b1011000 +
b101010 &
b101010 *
b0 (
b0 ,
b100010 )
#430000
1$
b11110010 %
b11110010 -
b111110010 .
0"
b10011100 '
b10011100 +
b10001110 &
b10001110 *
b1 (
b1 ,
b100011 )
#440000
0#
0$
b1 %
b1 -
b0 .
b1110011 '
b1110011 +
b100110 &
b100110 *
b101 (
b101 ,
b100100 )
#450000
1$
b1111100 %
b1111100 -
b101111100 .
b10110011 '
b10110011 +
b101111 &
b101111 *
b1 (
b1 ,
b100101 )
#460000
b1001101 %
b1001101 -
b101001101 .
b11110111 '
b11110111 +
b1000100 &
b1000100 *
b100110 )
#470000
0$
b1000010 %
b1000010 -
b0 .
b1011010 '
b1011010 +
b11100110 &
b11100110 *
b10 (
b10 ,
b100111 )
#480000
1#
b11111111 %
b11111111 -
b11011010 '
b11011010 +
b11101101 &
b11101101 *
b11 (
b11 ,
b101000 )
#490000
1$
b11010110 %
b11010110 -
b111010110 .
b11011111 '
b11011111 +
b10110101 &
b10110101 *
b1 (
b1 ,
b101001 )
#500000
0$
b10010100 %
b10010100 -
b0 .
b11010000 '
b11010000 +
b1000100 &
b1000100 *
b100 (
b100 ,
b101010 )
#510000
b10101111 %
b10101111 -
b1110 '
b1110 +
b10101011 &
b10101011 *
b11 (
b11 ,
b101011 )
#520000
0#
b1 %
b1 -
b11111101 '
b11111101 +
b10011010 &
b10011010 *
b101 (
b101 ,
b101100 )
#530000
b1000110 %
b1000110 -
b1001110 '
b1001110 +
b1010110 &
b1010110 *
b10 (
b10 ,
b101101 )
#540000
1$
b1010100 %
b1010100 -
b101010100 .
b10110110 '
b10110110 +
b1010 &
b1010 *
b1 (
b1 ,
b101110 )
#550000
b110001 %
b110001 -
b100110001 .
b10111000 '
b10111000 +
b1111001 &
b1111001 *
b0 (
b0 ,
b101111 )
#560000
1#
0$
b10010111 %
b10010111 -
b0 .
b100 '
b100 +
b10010011 &
b10010011 *
b100 (
b100 ,
b110000 )
#570000
b10001110 %
b10001110 -
b10001110 .
b1001101 '
b1001101 +
b11011011 &
b11011011 *
b1 (
b1 ,
b110001 )
#580000
0#
b1 %
b1 -
b0 .
b1110110 '
b1110110 +
b1101101 &
b1101101 *
b101 (
b101 ,
b110010 )
#590000
1!
b0 %
b0 -
b10010101 '
b10010101 +
b10110110 &
b10110110 *
b110011 )
#600000
1#
0!
b11111011 %
b11111011 -
b11111011 .
0"
b11110111 '
b11110111 +
b100 &
b100 *
b0 (
b0 ,
b110100 )
#610000
0#
b111100 %
b111100 -
b0 .
b10001000 '
b10001000 +
b10110100 &
b10110100 *
b100 (
b100 ,
b110101 )
#620000
1#
b11101111 %
b11101111 -
b11000111 '
b11000111 +
b101101 &
b101101 *
b11 (
b11 ,
b110110 )
#630000
0#
b100100 %
b100100 -
b100100 .
b11100 '
b11100 +
b1000 &
b1000 *
b0 (
b0 ,
b110111 )
#640000
b1000 %
b1000 -
b0 .
b101001 &
b101001 *
b10 (
b10 ,
b111000 )
#650000
1#
b11100111 %
b11100111 -
b111101 '
b111101 +
b11011010 &
b11011010 *
b100 (
b100 ,
b111001 )
#660000
0#
b11 %
b11 -
b1110011 '
b1110011 +
b1110000 &
b1110000 *
b111010 )
#670000
1!
b0 %
b0 -
b11111010 '
b11111010 +
b1011110 &
b1011110 *
b101 (
b101 ,
b111011 )
#680000
b10111001 '
b10111001 +
b11010 &
b11010 *
b111100 )
#690000
1#
0!
b11010110 %
b11010110 -
b11000000 '
b11000000 +
b10010110 &
b10010110 *
b11 (
b11 ,
b111101 )
#700000
b11111111 %
b11111111 -
b1111101 '
b1111101 +
b10110110 &
b10110110 *
b111110 )
#710000
0#
b1 %
b1 -
b1111000 '
b1111000 +
b10000110 &
b10000110 *
b101 (
b101 ,
b111111 )
#720000
b10100 %
b10100 -
b11001111 '
b11001111 +
b11011011 &
b11011011 *
b100 (
b100 ,
b1000000 )
#730000
1#
b10011011 %
b10011011 -
b1100001 '
b1100001 +
b11111010 &
b11111010 *
b1000001 )
#740000
b10100111 %
b10100111 -
b10000110 '
b10000110 +
b10100001 &
b10100001 *
b11 (
b11 ,
b1000010 )
#750000
1$
0#
b101010 %
b101010 -
b100101010 .
b110101 '
b110101 +
b11110101 &
b11110101 *
b0 (
b0 ,
b1000011 )
#760000
1#
b10000110 %
b10000110 -
b110000110 .
b11000101 '
b11000101 +
b11000001 &
b11000001 *
b1000100 )
#770000
b11011000 %
b11011000 -
b111011000 .
b1110011 '
b1110011 +
b1001011 &
b1001011 *
b1 (
b1 ,
b1000101 )
#780000
0#
0$
b1010 %
b1010 -
b0 .
b1001110 '
b1001110 +
b10001010 &
b10001010 *
b10 (
b10 ,
b1000110 )
#790000
0"
b1000 %
b1000 -
b1000 .
b10100001 '
b10100001 +
b10101001 &
b10101001 *
b1 (
b1 ,
b1000111 )
#800000
1#
b11111111 %
b11111111 -
b0 .
b10011111 '
b10011111 +
b11100110 &
b11100110 *
b11 (
b11 ,
b1001000 )
#810000
b10101111 %
b10101111 -
b10001101 '
b10001101 +
b101010 &
b101010 *
b1001001 )
#820000
0#
b1000001 %
b1000001 -
b1111001 '
b1111001 +
b111000 &
b111000 *
b100 (
b100 ,
b1001010 )
#830000
b1 %
b1 -
b10011 '
b10011 +
b11001010 &
b11001010 *
b101 (
b101 ,
b1001011 )
#840000
b1110001 %
b1110001 -
b10110110 '
b10110110 +
b11000111 &
b11000111 *
b100 (
b100 ,
b1001100 )
#850000
1!
b0 %
b0 -
b10111001 '
b10111001 +
b11000100 &
b11000100 *
b101 (
b101 ,
b1001101 )
#860000
1#
0!
b11001011 %
b11001011 -
b1111111 '
b1111111 +
b10110100 &
b10110100 *
b100 (
b100 ,
b1001110 )
#870000
0#
b1000 %
b1000 -
b1000 .
b11110010 '
b11110010 +
b11111010 &
b11111010 *
b1 (
b1 ,
b1001111 )
#880000
1#
b10111101 %
b10111101 -
b0 .
b10000100 '
b10000100 +
b10111101 &
b10111101 *
b11 (
b11 ,
b1010000 )
#890000
b10001000 %
b10001000 -
b10101001 '
b10101001 +
b11001010 &
b11001010 *
b10 (
b10 ,
b1010001 )
#900000
1$
b10010011 %
b10010011 -
b110010011 .
b11111011 '
b11111011 +
b10001110 &
b10001110 *
b1 (
b1 ,
b1010010 )
#910000
b10111000 %
b10111000 -
b110111000 .
b11001001 '
b11001001 +
b11101111 &
b11101111 *
b0 (
b0 ,
b1010011 )
#920000
0$
b11111111 %
b11111111 -
b0 .
b10001111 '
b10001111 +
b1110101 &
b1110101 *
b11 (
b11 ,
b1010100 )
#930000
0#
b100110 %
b100110 -
b10101110 '
b10101110 +
b10001000 &
b10001000 *
b100 (
b100 ,
b1010101 )
#940000
1#
b10111010 %
b10111010 -
b101000 '
b101000 +
b10010010 &
b10010010 *
b1010110 )
#950000
1$
0#
b1101 %
b1101 -
b100001101 .
b11000010 '
b11000010 +
b1001011 &
b1001011 *
b0 (
b0 ,
b1010111 )
#960000
0$
1#
b11111001 %
b11111001 -
b11111001 .
b11101100 '
b11101100 +
b1101 &
b1101 *
b1011000 )
#970000
b11010111 %
b11010111 -
b0 .
b10000110 '
b10000110 +
b11010001 &
b11010001 *
b11 (
b11 ,
b1011001 )
#980000
1$
0#
b10011 %
b10011 -
b100010011 .
b11011000 '
b11011000 +
b111011 &
b111011 *
b0 (
b0 ,
b1011010 )
#990000
0$
b1011111 %
b1011111 -
b0 .
b1011011 '
b1011011 +
b1010110 &
b1010110 *
b11 (
b11 ,
b1011011 )
#1000000
1!
b0 %
b0 -
b1110011 '
b1110011 +
b100 &
b100 *
b10 (
b10 ,
b1011100 )
#1010000
0!
b10000 %
b10000 -
b10111000 '
b10111000 +
b10010 &
b10010 *
b1011101 )
#1020000
1$
1#
b10000110 %
b10000110 -
b110000110 .
b10100001 '
b10100001 +
b11100101 &
b11100101 *
b0 (
b0 ,
b1011110 )
#1030000
0$
b11001001 %
b11001001 -
b0 .
b11001000 '
b11001000 +
b10000001 &
b10000001 *
b11 (
b11 ,
b1011111 )
#1040000
b10111111 %
b10111111 -
b11111 '
b11111 +
b10100001 &
b10100001 *
b1100000 )
#1050000
b11101110 %
b11101110 -
b11101110 .
b10010110 '
b10010110 +
b1011000 &
b1011000 *
b0 (
b0 ,
b1100001 )
#1060000
b10010110 %
b10010110 -
b0 .
b10010 &
b10010 *
b11 (
b11 ,
b1100010 )
#1070000
0#
b1000101 %
b1000101 -
b11101101 '
b11101101 +
b1010101 &
b1010101 *
b10 (
b10 ,
b1100011 )
#1080000
b1100100 )
