tutorial-2/src/mux8to1.v
module mux8to1
(
    input wire [7 : 0] d,
    input wire [2 : 0] sel,
    input wire en_n,
    output reg q
);
    
    always @(*) begin
        if (en_n) begin
            q = 1'b0; 
        end else begin
            case (sel)
                3'b000:  q = d[0];
                3'b001:  q = d[1];
                3'b010:  q = d[2]; 
                3'b011:  q = d[3];
                3'b100:  q = d[4];
                3'b101:  q = d[5];
                3'b110:  q = d[6];
                3'b111:  q = d[7];
                default: q = 1'b0;
            endcase
        end
    end
endmodule

tutorial-2/test/tb/tb_mux8to1.v
`timescale 1ns/1ps

module tb_mux8to1;
    reg  [7:0] d;
    reg  [2:0] sel;
    reg        en_n;
    wire       q;

    mux8to1 uut (
        .d(d), .sel(sel), .en_n(en_n), .q(q)
    );

    integer i;

    initial begin
        $dumpfile("wave_mux.vcd");
        $dumpvars(0, tb_mux8to1);

        d = 8'b1010_0110;
        
        en_n = 1'b1;
        for (i = 0; i < 8; i = i + 1) begin
            sel = i[2:0]; #10;
        end

        en_n = 1'b0;
        for (i = 0; i < 8; i = i + 1) begin
            sel = i[2:0]; #10;
        end

        $finish;
    end
endmodule

tutorial-2/test/wave/wave_mux.vcd
$date
	Sun Sep 27 21:51:55 2026
$end
$version
	Icarus Verilog
$end
$timescale
	1ps
$end
$scope module tb_mux8to1 $end
$var wire 1 ! q $end
$var reg 8 " d [7:0] $end
$var reg 1 # en_n $end
$var reg 3 $ sel [2:0] $end
$var integer 32 % i [31:0] $end
$scope module uut $end
$var wire 8 & d [7:0] $end
$var wire 1 # en_n $end
$var wire 3 ' sel [2:0] $end
$var reg 1 ! q $end
$upscope $end
$upscope $end
$enddefinitions $end
#0
$dumpvars
b0 '
b10100110 &
b0 %
b0 $
1#
b10100110 "
0!
$end
#10000
b1 $
b1 '
b1 %
#20000
b10 $
b10 '
b10 %
#30000
b11 $
b11 '
b11 %
#40000
b100 $
b100 '
b100 %
#50000
b101 $
b101 '
b101 %
#60000
b110 $
b110 '
b110 %
#70000
b111 $
b111 '
b111 %
#80000
b0 $
b0 '
0#
b0 %
#90000
1!
b1 $
b1 '
b1 %
#100000
b10 $
b10 '
b10 %
#110000
0!
b11 $
b11 '
b11 %
#120000
b100 $
b100 '
b100 %
#130000
1!
b101 $
b101 '
b101 %
#140000
0!
b110 $
b110 '
b110 %
#150000
1!
b111 $
b111 '
b111 %
#160000
b1000 %
